docs/conf.py
examples/custom_pipeline_example/custom_grpo.py
examples/custom_reward/rewardfunc_gsm8k.py
examples/data_preprocess/deepscaler.py
examples/data_preprocess/geo3k.py
examples/data_preprocess/gsm8k.py
examples/data_preprocess/math_dataset.py
examples/data_preprocess/mm_eureka.py
examples/experimental/marft/config/code_env.py
examples/experimental/marft/config/math_env.py
examples/experimental/marft/config/process.py
siirl/__init__.py
siirl/_version.py
siirl/main_dag.py
siirl/dag_worker/__init__.py
siirl/dag_worker/checkpoint_manager.py
siirl/dag_worker/constants.py
siirl/dag_worker/core_algos.py
siirl/dag_worker/dag_utils.py
siirl/dag_worker/dagworker.py
siirl/dag_worker/data_structures.py
siirl/dag_worker/metric_aggregator.py
siirl/dag_worker/metrics_collector.py
siirl/dag_worker/validator.py
siirl/data_coordinator/__init__.py
siirl/data_coordinator/data_buffer.py
siirl/data_coordinator/protocol.py
siirl/data_coordinator/sample.py
siirl/data_coordinator/dataloader/__init__.py
siirl/data_coordinator/dataloader/data_loader_node.py
siirl/data_coordinator/dataloader/embodied_preprocess.py
siirl/data_coordinator/dataloader/partitioned_dataset.py
siirl/data_coordinator/dataloader/vision_utils.py
siirl/engine/__init__.py
siirl/engine/fsdp_workers.py
siirl/engine/megatron_workers.py
siirl/engine/actor/__init__.py
siirl/engine/actor/base.py
siirl/engine/actor/dp_actor.py
siirl/engine/actor/embodied_actor.py
siirl/engine/actor/megatron_actor.py
siirl/engine/base_worker/__init__.py
siirl/engine/base_worker/resouce_pool.py
siirl/engine/base_worker/base/__init__.py
siirl/engine/base_worker/base/worker.py
siirl/engine/base_worker/megatron/__init__.py
siirl/engine/base_worker/megatron/npu_mbridge_patch.py
siirl/engine/base_worker/megatron/worker.py
siirl/engine/base_worker/register_center/__init__.py
siirl/engine/base_worker/register_center/register_center.py
siirl/engine/critic/__init__.py
siirl/engine/critic/base.py
siirl/engine/critic/dp_critic.py
siirl-0.2.0.dist-info/licenses/LICENSE
siirl-0.2.0.dist-info/METADATA
siirl-0.2.0.dist-info/WHEEL
siirl-0.2.0.dist-info/top_level.txt
siirl-0.2.0.dist-info/RECORD
