Metadata-Version: 2.4
Name: siirl
Version: 0.2.0
Summary: siirl: A Decentralized Multi-Agent Reinforcement Learning Framework
Author-email: Shanghai Innovation Institute - AI Infra Team <llm19900326@gmail.com>
License: 
Project-URL: Homepage, https://github.com/sii-research/siiRL
Project-URL: Bug Tracker, https://github.com/sii-research/siiRL/issues
Project-URL: Repository, https://github.com/sii-research/siiRL
Keywords: reinforcement learning,multi-agent,decentralized,rl,ai
Classifier: Development Status :: 4 - Beta
Classifier: Intended Audience :: Developers
Classifier: Intended Audience :: Science/Research
Classifier: License :: OSI Approved :: Apache Software License
Classifier: Programming Language :: Python :: 3
Classifier: Programming Language :: Python :: 3.10
Classifier: Programming Language :: Python :: 3.11
Classifier: Programming Language :: Python :: 3.12
Classifier: Operating System :: OS Independent
Classifier: Topic :: Scientific/Engineering :: Artificial Intelligence
Requires-Python: >=3.8
License-File: LICENSE
Requires-Dist: accelerate
Requires-Dist: codetiming
Requires-Dist: datasets>=4.0.0
Requires-Dist: dill
Requires-Dist: hydra-core
Requires-Dist: numpy
Requires-Dist: pandas
Requires-Dist: peft
Requires-Dist: pyarrow>=19.0.0
Requires-Dist: pybind11
Requires-Dist: pylatexenc
Requires-Dist: ray[default]>=2.47.1
Requires-Dist: torchdata
Requires-Dist: tensordict!=0.9.0,<=0.9.1,>=0.8.0
Requires-Dist: wandb
Requires-Dist: tensorboard
Requires-Dist: mathruler
Requires-Dist: math_verify
Requires-Dist: timm
Requires-Dist: imageio
Requires-Dist: loguru
Requires-Dist: packaging>=20.0
Requires-Dist: dacite
Requires-Dist: qwen_vl_utils
Requires-Dist: scipy
Requires-Dist: fastapi
Requires-Dist: transformers
Requires-Dist: math-verify
Requires-Dist: vllm>=0.8.5.post1
Provides-Extra: dev
Requires-Dist: ruff; extra == "dev"
Requires-Dist: pytest; extra == "dev"
Requires-Dist: build; extra == "dev"
Requires-Dist: twine; extra == "dev"
Requires-Dist: pre-commit; extra == "dev"
Requires-Dist: py-spy; extra == "dev"
Provides-Extra: test
Requires-Dist: pytest; extra == "test"
Requires-Dist: pre-commit; extra == "test"
Requires-Dist: py-spy; extra == "test"
Requires-Dist: pyext; extra == "test"
Provides-Extra: geo
Requires-Dist: mathruler; extra == "geo"
Provides-Extra: gpu
Requires-Dist: liger-kernel; extra == "gpu"
Requires-Dist: flash-attn; extra == "gpu"
Provides-Extra: sglang
Requires-Dist: tensordict!=0.9.0,<=0.9.1,>=0.8.0; extra == "sglang"
Requires-Dist: sglang[all]>=0.4.6.post5; extra == "sglang"
Requires-Dist: torch-memory-saver>=0.0.5; extra == "sglang"
Requires-Dist: torch>=2.6.0; extra == "sglang"
Dynamic: license-file
